assistant/__init__.py
assistant/app.py
assistant/api/__init__.py
assistant/api/requests.py
assistant/config/__init__.py
assistant/config/log_config.py
assistant/core/__init__.py
assistant/core/conversation.py
assistant/core/intent_router.py
assistant/core/enums/__init__.py
assistant/prompts/__init__.py
assistant/prompts/intent_prompt.j2
assistant/prompts/summarization.j2
assistant/prompts/system_prompt.j2
assistant/services/openai_client.py
assistant/utils/Dockerfile
assistant/utils/__init__.py
assistant/utils/requirements.txt
assistant/voice/__init__.py
assistant/voice/mic_stream.py
assistant/voice/test.py
assistant/voice/tts_player.py
full_duplex_assistant-0.1.1.dist-info/METADATA
full_duplex_assistant-0.1.1.dist-info/WHEEL
full_duplex_assistant-0.1.1.dist-info/licenses/LICENSE
full_duplex_assistant-0.1.1.dist-info/RECORD
