Metadata-Version: 2.4
Name: full-duplex-assistant
Version: 0.1.1
Summary: Real-time full-duplex voice assistant (FastAPI backend)
Project-URL: Homepage, https://github.com/leo007-htun/full_duplex_assistant
Project-URL: Issues, https://github.com/leo007-htun/full_duplex_assistant/issues
Author: Sithu Ye Htun (Leo)
License: MIT License
License-File: LICENSE
Requires-Python: >=3.9
